simple_tk_stopwatch/__init__.py
simple_tk_stopwatch/app.py
simple_tk_stopwatch-0.1.2.dist-info/LICENSE
simple_tk_stopwatch-0.1.2.dist-info/METADATA
simple_tk_stopwatch-0.1.2.dist-info/WHEEL
simple_tk_stopwatch-0.1.2.dist-info/entry_points.txt
simple_tk_stopwatch-0.1.2.dist-info/top_level.txt
simple_tk_stopwatch-0.1.2.dist-info/RECORD
