Metadata-Version: 2.2
Name: simple-tk-stopwatch
Version: 0.1.2
Summary: Simple stopwatch window in tkinter
License: MIT
Project-URL: Homepage, https://github.com/shockwavebot/simple-tk-stopwatch
Classifier: Programming Language :: Python :: 3
Classifier: Operating System :: OS Independent
Requires-Python: >=3.13
License-File: LICENSE
Requires-Dist: twine>=6.1.0
